tlm/__init__.py
tlm/ansiblecaller.py
tlm/configfilecopier.py
tlm/configorchestrator.py
tlm/directorycomparer.py
tlm/exceptionlogger.py
tlm/exechelper.py
tlm/filesync.py
tlm/gitcaller.py
tlm/jinjatransformer.py
tlm/management_interface.py
tlm/nodeattacher.py
tlm/towalinkmanager.py
tlm/ansible/node.yml
tlm/ansible/roles/bird/files/etc_apt_preferencesd/debian-testing
tlm/ansible/roles/bird/tasks/main.yml
tlm/ansible/roles/bird-lg-proxy/files/etc_initd/towalink_bird-lg-proxy
tlm/ansible/roles/bird-lg-proxy/files/etc_systemd_system/towalink_bird-lg-proxy.service
tlm/ansible/roles/bird-lg-proxy/tasks/main.yml
tlm/ansible/roles/nodecfg/files/opt_towalink_scripts/rsync-nodecfg.sh
tlm/ansible/roles/nodecfg/tasks/main.yml
tlm/ansible/roles/nodeconfig/files/opt_towalink_scripts/rsync-nodecfg.sh
tlm/ansible/roles/nodeconfig/tasks/main.yml
tlm/ansible/roles/startup/files/etc_initd/towalink_startup
tlm/ansible/roles/startup/files/etc_systemd_system/towalink_startup.service
tlm/ansible/roles/startup/files/opt_towalink_startup/towalink.sh
tlm/ansible/roles/startup/files/opt_towalink_startup/scripts/wireguard
tlm/ansible/roles/startup/tasks/main.yml
tlm/ansible/roles/system/files/unused_etc_sysctld/towalink.conf
tlm/ansible/roles/system/tasks/main.yml
tlm/ansible/vars/external_vars.yml
tlm/configmanager/__init__.py
tlm/configmanager/configmanager.py
tlm/configmanager/generatedconfig.py
tlm/configmanager/nodeconfig.py
tlm/configmanager/siteconfig.py
tlm/configmanager/tomlconfig.py
tlm/configmanager/tomlconfighierarchy.py
tlm/configmanager/wireguard.py
tlm/configmanager/yamlconfig.py
tlm/healthcheck/__init__.py
tlm/healthcheck/cmdexec.py
tlm/healthcheck/ping.py
tlm/skeleton/LICENSE
tlm/skeleton/bird.conf.jinja
tlm/skeleton/bird_neighbors.conf.jinja
tlm/skeleton/bird_site-template.conf.jinja
tlm/skeleton/config.toml
tlm/skeleton/startup_loopback.jinja
tlm/skeleton/tlwg.conf.jinja
towalink_tlm-0.3.2.dist-info/LICENSE
towalink_tlm-0.3.2.dist-info/METADATA
towalink_tlm-0.3.2.dist-info/WHEEL
towalink_tlm-0.3.2.dist-info/entry_points.txt
towalink_tlm-0.3.2.dist-info/top_level.txt
towalink_tlm-0.3.2.dist-info/RECORD
