Metadata-Version: 2.1
Name: towalink-tlm
Version: 0.3.2
Summary: command line tool for configuring and managing a Towalink installation
Home-page: https://www.towalink.net
Author: The Towalink Project
Author-email: pypi.tlm@towalink.net
Project-URL: Project homepage, https://www.towalink.net
Project-URL: Repository, https://www.github.com/towalink/tlm
Project-URL: Documentation, https://towalink.readthedocs.io
Keywords: Towalink VPN SD-WAN WireGuard
Classifier: Programming Language :: Python
Classifier: Programming Language :: Python :: 3
Classifier: License :: OSI Approved :: GNU Affero General Public License v3 or later (AGPLv3+)
Classifier: Operating System :: POSIX :: Linux
Classifier: Development Status :: 4 - Beta
Classifier: Intended Audience :: System Administrators
Classifier: Intended Audience :: Information Technology
Classifier: Intended Audience :: Telecommunications Industry
Classifier: Topic :: System :: Networking
Requires-Python: >=3.6
License-File: LICENSE
Requires-Dist: python-configuration
Requires-Dist: jinja2
Requires-Dist: pyyaml
Requires-Dist: toml
Requires-Dist: tomlkit
Requires-Dist: ansible
Requires-Dist: wgconfig >=1.0.1
